pydispo/__init__.py
pydispo/pydispo.py
pydispo-20.10b1.dist-info/METADATA
pydispo-20.10b1.dist-info/WHEEL
pydispo-20.10b1.dist-info/entry_points.txt
pydispo-20.10b1.dist-info/top_level.txt
pydispo-20.10b1.dist-info/RECORD
