Metadata-Version: 2.1
Name: pydispo
Version: 20.10b1
Summary: A Disposable Mailbox Powered by Pure-Python
Home-page: https://github.com/aakash30jan/pydispo
Author: Aakash Patil
License: GPL
Keywords: privacy disposable-email temporary-email
Platform: any
Classifier: Programming Language :: Python 
Classifier: Programming Language :: Python :: 2
Classifier: Programming Language :: Python :: 3
Classifier: License :: OSI Approved :: GNU General Public License v3 (GPLv3)
Classifier: Operating System :: OS Independent
Requires-Dist: requests
